cli/FRONTEND_INTEGRATION.md
cli/PYPI_QUICK_START.md
cli/PYPI_UPLOAD.md
cli/README.md
cli/SETUP.md
cli/__init__.py
cli/agent_spec.py
cli/api_client.py
cli/auth.py
cli/commands.py
cli/dockerfile_gen.py
cli/main.py
simultaneous_cli-0.1.2.dist-info/METADATA
simultaneous_cli-0.1.2.dist-info/WHEEL
simultaneous_cli-0.1.2.dist-info/entry_points.txt
simultaneous_cli-0.1.2.dist-info/top_level.txt
simultaneous_cli-0.1.2.dist-info/RECORD
