Metadata-Version: 2.4
Name: simultaneous-cli
Version: 0.1.2
Summary: CLI for Simultaneous SDK
Author: Simultaneous Team
License: MIT
Keywords: cli,simultaneous,agents,automation,command-line
Classifier: Development Status :: 3 - Alpha
Classifier: Intended Audience :: Developers
Classifier: Programming Language :: Python :: 3
Classifier: Programming Language :: Python :: 3.11
Classifier: Programming Language :: Python :: 3.12
Requires-Python: >=3.11
Requires-Dist: typer>=0.12.0
Requires-Dist: rich>=13.0.0
Requires-Dist: supabase>=2.0.0
Requires-Dist: python-dotenv>=1.0.0
Requires-Dist: httpx>=0.24.0
Requires-Dist: pydantic>=2.0.0
Requires-Dist: pyyaml>=6.0.0
Provides-Extra: dev
Requires-Dist: pytest>=7.4.0; extra == "dev"
Requires-Dist: pytest-asyncio>=0.21.0; extra == "dev"
Requires-Dist: mypy>=1.0.0; extra == "dev"
Requires-Dist: ruff>=0.1.0; extra == "dev"
